originstamp_client/__init__.py
originstamp_client/api_client.py
originstamp_client/configuration.py
originstamp_client/rest.py
originstamp_client/api/__init__.py
originstamp_client/api/api_key_api.py
originstamp_client/api/bulk_api.py
originstamp_client/api/proof_api.py
originstamp_client/api/scheduler_api.py
originstamp_client/api/timestamp_api.py
originstamp_client/api/webhook_api.py
originstamp_client/models/__init__.py
originstamp_client/models/currency_model.py
originstamp_client/models/default_of_download_link_response.py
originstamp_client/models/default_of_list_of_currency_model.py
originstamp_client/models/default_of_timestamp_data.py
originstamp_client/models/default_of_timestamp_response.py
originstamp_client/models/default_of_void.py
originstamp_client/models/default_of_webhook_response.py
originstamp_client/models/default_ofstring.py
originstamp_client/models/default_usage_response.py
originstamp_client/models/download_link_response.py
originstamp_client/models/manual_webhook_request.py
originstamp_client/models/notification.py
originstamp_client/models/proof_request.py
originstamp_client/models/timestamp_bulk_request.py
originstamp_client/models/timestamp_data.py
originstamp_client/models/timestamp_request.py
originstamp_client/models/timestamp_response.py
originstamp_client/models/usage_response.py
originstamp_client/models/webhook_request.py
originstamp_client/models/webhook_response.py
originstamp_client-2.0.1.dist-info/LICENSE
originstamp_client-2.0.1.dist-info/METADATA
originstamp_client-2.0.1.dist-info/WHEEL
originstamp_client-2.0.1.dist-info/top_level.txt
originstamp_client-2.0.1.dist-info/RECORD
